CHANGES.html
DisplayCAL-3DLUT-maker.pyw
DisplayCAL-VRML-to-X3D-converter-console.py
DisplayCAL-VRML-to-X3D-converter.pyw
DisplayCAL-apply-profiles.pyw
DisplayCAL-curve-viewer.pyw
DisplayCAL-eeColor-to-madVR-converter.py
DisplayCAL-profile-info.pyw
DisplayCAL-scripting-client.pyw
DisplayCAL-synthprofile.pyw
DisplayCAL-testchart-editor.pyw
DisplayCAL.pyw
LICENSE.txt
MANIFEST.in
README-fr.html
README.html
README.md
VERSION
pyproject.toml
requirements.txt
setup.py
/Users/eoyilmaz/temp/displaycal-py3/DisplayCAL/../dist/copyright
/Users/eoyilmaz/temp/displaycal-py3/DisplayCAL/../misc/displaycal-readme
DisplayCAL/ColorLookupTable.fx
DisplayCAL/RealDisplaySizeMM.py
DisplayCAL/__init__.py
DisplayCAL/__main__.py
DisplayCAL/__version__.py
DisplayCAL/argyll.py
DisplayCAL/argyll_RGB2XYZ.py
DisplayCAL/argyll_cgats.py
DisplayCAL/argyll_instruments.py
DisplayCAL/argyll_names.py
DisplayCAL/audio.py
DisplayCAL/beep.wav
DisplayCAL/camera_shutter.wav
DisplayCAL/ccmx.py
DisplayCAL/cgats.py
DisplayCAL/chromecast_patterngenerator.py
DisplayCAL/colord.py
DisplayCAL/colormath.py
DisplayCAL/config.py
DisplayCAL/cubeiterator.py
DisplayCAL/debughelpers.py
DisplayCAL/defaultpaths.py
DisplayCAL/demjson_compat.py
DisplayCAL/display_cal.py
DisplayCAL/edid.py
DisplayCAL/embeddedimage.py
DisplayCAL/encodedstdio.py
DisplayCAL/encoding.py
DisplayCAL/floatspin.py
DisplayCAL/freeze.py
DisplayCAL/gtypes.py
DisplayCAL/icc_profile.py
DisplayCAL/imfile.py
DisplayCAL/jsondict.py
DisplayCAL/jspacker.py
DisplayCAL/lazydict.py
DisplayCAL/linear.cal
DisplayCAL/localization.py
DisplayCAL/log.py
DisplayCAL/madvr.py
DisplayCAL/main.py
DisplayCAL/meta.py
DisplayCAL/multiprocess.py
DisplayCAL/network.py
DisplayCAL/options.py
DisplayCAL/patterngenerators.py
DisplayCAL/pnp.ids
DisplayCAL/postinstall.py
DisplayCAL/profile_loader.py
DisplayCAL/pyi_md5pickuphelper.py
DisplayCAL/report.py
DisplayCAL/safe_print.py
DisplayCAL/setup.py
DisplayCAL/systrayicon.py
DisplayCAL/taskbar.py
DisplayCAL/taskscheduler.py
displaycal.egg-info/PKG-INFO
displaycal.egg-info/SOURCES.txt
displaycal.egg-info/dependency_links.txt
displaycal.egg-info/requires.txt
displaycal.egg-info/top_level.txt
