Metadata-Version: 2.4
Name: displaycal
Version: 3.9.17
Summary: Display calibration and profiling with a focus on accuracy and versatility
Home-page: https://displaycal.net/
Download-URL: https://github.com/eoyilmaz/displaycal-py3/releases/download/3.9.17/DisplayCAL-3.9.17.tar.gz
Author: Florian Hoech, Erkan Ozgur Yilmaz, Patrick Zwerschke
Author-email: Florian Höch <florian@displaycal.net>, Erkan Özgür Yılmaz <eoyilmaz@gmail.com>, Patrick Zwerschke <patrick@p5k.org>
Maintainer-email: Erkan Özgür Yılmaz <eoyilmaz@gmail.com>
License-Expression: GPL-3.0-or-later
Project-URL: Home Page, https://displaycal.net/
Project-URL: GitHub, https://github.com/eoyilmaz/displaycal-py3
Project-URL: Repository, https://github.com/eoyilmaz/displaycal-py3.git
Project-URL: Download, https://github.com/eoyilmaz/displaycal-py3/releases/
Platform: Python >= 3.8 <= 3.13
Platform: Linux/Unix with X11
Platform: Mac OS X >= 10.4
Platform: Windows 2000 and newer
Classifier: Development Status :: 5 - Production/Stable
Classifier: Environment :: MacOS X
Classifier: Environment :: Win32 (MS Windows)
Classifier: Environment :: X11 Applications
Classifier: Intended Audience :: End Users/Desktop
Classifier: Operating System :: OS Independent
Classifier: Programming Language :: Python :: 3.9
Classifier: Programming Language :: Python :: 3.10
Classifier: Programming Language :: Python :: 3.11
Classifier: Programming Language :: Python :: 3.12
Classifier: Programming Language :: Python :: 3.13
Classifier: Topic :: Multimedia :: Graphics
Requires: wxPython (>= 2.8.11)
Provides: DisplayCAL
Requires-Python: >=3.9
License-File: LICENSE.txt
Requires-Dist: build
Requires-Dist: certifi
Requires-Dist: comtypes; sys_platform == "win32"
Requires-Dist: dbus-python; sys_platform == "linux"
Requires-Dist: distro
Requires-Dist: numpy
Requires-Dist: Pillow
Requires-Dist: protobuf
Requires-Dist: PyChromecast
Requires-Dist: pywin32; sys_platform == "win32"
Requires-Dist: Send2Trash
Requires-Dist: WMI; sys_platform == "win32"
Requires-Dist: wxPython>=4.2.2
Requires-Dist: zeroconf
Dynamic: author
Dynamic: download-url
Dynamic: home-page
Dynamic: license-file
Dynamic: platform
Dynamic: provides
Dynamic: requires
